LICENSE
MANIFEST.in
README
ngblog.py
setup.py
ngblog.egg-info/PKG-INFO
ngblog.egg-info/SOURCES.txt
ngblog.egg-info/dependency_links.txt
ngblog.egg-info/entry_points.txt
ngblog.egg-info/requires.txt
ngblog.egg-info/top_level.txt