Metadata-Version: 1.0
Name: ngblog
Version: 0.1.2
Summary: A simple and easy to use plain-text-like blogging-engine.
Home-page: http://nerdgordo.com/git/?p=ngblog.git
Author: Nerd Gordo
Author-email: nerdgordo@nerdgordo.com
License: BSD
Platform: UNKNOWN
